README.md
setup.py
test.py
libhydrogen/hydrogen.c
libhydrogen/hydrogen.h
libhydrogen/impl/common.h
libhydrogen/impl/core.h
libhydrogen/impl/gimli-core.h
libhydrogen/impl/hash.h
libhydrogen/impl/hydrogen_p.h
libhydrogen/impl/kdf.h
libhydrogen/impl/kx.h
libhydrogen/impl/pwhash.h
libhydrogen/impl/random.h
libhydrogen/impl/secretbox.h
libhydrogen/impl/sign.h
libhydrogen/impl/x25519.h
libhydrogen/impl/gimli-core/portable.h
libhydrogen/impl/gimli-core/sse2.h
pyhy/__init__.py
pyhy/__version__.py
pyhy/bind.py
pyhy/pyhy.h
pyhy.egg-info/PKG-INFO
pyhy.egg-info/SOURCES.txt
pyhy.egg-info/dependency_links.txt
pyhy.egg-info/requires.txt
pyhy.egg-info/top_level.txt